{
  "generated_at": "2026-07-03T02:54:29.408525+00:00",
  "dart_available": true,
  "krx_available": false,
  "price_source": "kis_proxy",
  "latest_price_source": "kis_proxy",
  "update_mode": "backfill_merge",
  "previous_generated_at": "2026-07-02T21:57:22.276800+00:00",
  "companies_count": 2539,
  "events_count": 1051,
  "holdings_count": 2550,
  "price_reactions_count": 1051,
  "latest_prices_count": 600,
  "warnings": [
    "Incremental update merged with the committed dataset instead of rebuilding the full universe.",
    "Holding snapshots are refreshed only for companies with incremental event disclosures; existing all-market snapshots are preserved.",
    "OpenDART incremental disclosure window: 20260623 to 20260702.",
    "OpenDART incremental event company scope: 74 companies.",
    "OpenDART holding scan source: stock_totals.",
    "Listed issue master source: naver.",
    "Price reactions use kis_proxy when configured; otherwise they remain missing.",
    "Latest prices use kis_proxy when configured; otherwise market caps remain missing.",
    "Backfill run 20260601-20260703-28634867397 merged 17 new events and skipped 224 duplicates.",
    "Backfilled historical price reactions are initialized as missing until price enrichment is run.",
    "Execution result reports stored: 85 (4 unlinked)."
  ],
  "last_backfill_run_id": "20260601-20260703-28634867397",
  "last_backfill_new_events_count": 17,
  "last_backfill_duplicate_events_count": 224,
  "executions_count": 85
}
