{
  "status": "000",
  "message": "정상",
  "page_no": 3,
  "page_count": 100,
  "total_count": 1888,
  "total_page": 19,
  "list": [
    {
      "corp_code": "00615723",
      "corp_name": "알엔티엑스",
      "stock_code": "123010",
      "corp_cls": "K",
      "report_nm": "증권발행결과(자율공시)              ",
      "rcept_no": "20260519900467",
      "flr_nm": "알엔티엑스",
      "rcept_dt": "20260519",
      "rm": "코"
    },
    {
      "corp_code": "01244601",
      "corp_name": "카카오페이",
      "stock_code": "377300",
      "corp_cls": "Y",
      "report_nm": "기업설명회(IR)개최(안내공시)              ",
      "rcept_no": "20260519800442",
      "flr_nm": "카카오페이",
      "rcept_dt": "20260519",
      "rm": "유"
    },
    {
      "corp_code": "01009789",
      "corp_name": "코스맥스",
      "stock_code": "192820",
      "corp_cls": "Y",
      "report_nm": "기업설명회(IR)개최(안내공시)              ",
      "rcept_no": "20260519800441",
      "flr_nm": "코스맥스",
      "rcept_dt": "20260519",
      "rm": "유"
    },
    {
      "corp_code": "01622331",
      "corp_name": "벨로크",
      "stock_code": "424760",
      "corp_cls": "K",
      "report_nm": "주권매매거래정지해제              (액면병합 주권 변경상장)",
      "rcept_no": "20260519900457",
      "flr_nm": "코스닥시장본부",
      "rcept_dt": "20260519",
      "rm": "코"
    },
    {
      "corp_code": "00104573",
      "corp_name": "국일제지",
      "stock_code": "078130",
      "corp_cls": "K",
      "report_nm": "주권매매거래정지해제              (액면병합 주권 변경상장)",
      "rcept_no": "20260519900452",
      "flr_nm": "코스닥시장본부",
      "rcept_dt": "20260519",
      "rm": "코"
    },
    {
      "corp_code": "00260383",
      "corp_name": "대한유화",
      "stock_code": "006650",
      "corp_cls": "Y",
      "report_nm": "최대주주등소유주식변동신고서              ",
      "rcept_no": "20260519800456",
      "flr_nm": "대한유화",
      "rcept_dt": "20260519",
      "rm": "유"
    },
    {
      "corp_code": "00567897",
      "corp_name": "에스비비테크",
      "stock_code": "389500",
      "corp_cls": "K",
      "report_nm": "단일판매ㆍ공급계약체결              ",
      "rcept_no": "20260519900397",
      "flr_nm": "에스비비테크",
      "rcept_dt": "20260519",
      "rm": "코"
    },
    {
      "corp_code": "00225742",
      "corp_name": "LS마린솔루션",
      "stock_code": "060370",
      "corp_cls": "K",
      "report_nm": "[기재정정]단일판매ㆍ공급계약체결              ",
      "rcept_no": "20260519900419",
      "flr_nm": "LS마린솔루션",
      "rcept_dt": "20260519",
      "rm": "코"
    },
    {
      "corp_code": "01042711",
      "corp_name": "글로벌텍스프리",
      "stock_code": "204620",
      "corp_cls": "K",
      "report_nm": "기업설명회(IR)개최              ",
      "rcept_no": "20260519900446",
      "flr_nm": "글로벌텍스프리",
      "rcept_dt": "20260519",
      "rm": "코"
    },
    {
      "corp_code": "00111421",
      "corp_name": "휴니드테크놀러지스",
      "stock_code": "005870",
      "corp_cls": "Y",
      "report_nm": "단일판매ㆍ공급계약체결              ",
      "rcept_no": "20260519800415",
      "flr_nm": "휴니드테크놀러지스",
      "rcept_dt": "20260519",
      "rm": "유"
    },
    {
      "corp_code": "00156859",
      "corp_name": "다올투자증권",
      "stock_code": "030210",
      "corp_cls": "Y",
      "report_nm": "최대주주등소유주식변동신고서              ",
      "rcept_no": "20260519800430",
      "flr_nm": "다올투자증권",
      "rcept_dt": "20260519",
      "rm": "유"
    },
    {
      "corp_code": "00579139",
      "corp_name": "한국맥널티",
      "stock_code": "222980",
      "corp_cls": "K",
      "report_nm": "자산재평가결과(자율공시)              ",
      "rcept_no": "20260519900428",
      "flr_nm": "한국맥널티",
      "rcept_dt": "20260519",
      "rm": "코"
    },
    {
      "corp_code": "00563518",
      "corp_name": "비나텍",
      "stock_code": "126340",
      "corp_cls": "K",
      "report_nm": "기업설명회(IR)개최              ",
      "rcept_no": "20260519900423",
      "flr_nm": "비나텍",
      "rcept_dt": "20260519",
      "rm": "코"
    },
    {
      "corp_code": "00542074",
      "corp_name": "LSK아이로봇",
      "stock_code": "091970",
      "corp_cls": "K",
      "report_nm": "타인에대한채무보증결정              ",
      "rcept_no": "20260519900403",
      "flr_nm": "LSK아이로봇",
      "rcept_dt": "20260519",
      "rm": "코"
    },
    {
      "corp_code": "00220057",
      "corp_name": "GC메디아이",
      "stock_code": "032620",
      "corp_cls": "K",
      "report_nm": "기업설명회(IR)개최              ",
      "rcept_no": "20260519900416",
      "flr_nm": "GC메디아이",
      "rcept_dt": "20260519",
      "rm": "코"
    },
    {
      "corp_code": "00297448",
      "corp_name": "플래스크",
      "stock_code": "041590",
      "corp_cls": "K",
      "report_nm": "기타시장안내              (코스닥시장위원회 개최 결과 및 상장폐지 결정 안내)",
      "rcept_no": "20260519900404",
      "flr_nm": "코스닥시장본부",
      "rcept_dt": "20260519",
      "rm": "코"
    },
    {
      "corp_code": "01251489",
      "corp_name": "라온피플",
      "stock_code": "300120",
      "corp_cls": "K",
      "report_nm": "주주명부폐쇄기간또는기준일설정              ",
      "rcept_no": "20260519900409",
      "flr_nm": "라온피플",
      "rcept_dt": "20260519",
      "rm": "코"
    },
    {
      "corp_code": "01585155",
      "corp_name": "오픈놀",
      "stock_code": "440320",
      "corp_cls": "K",
      "report_nm": "[기재정정]기업설명회(IR)개최              ",
      "rcept_no": "20260519900395",
      "flr_nm": "오픈놀",
      "rcept_dt": "20260519",
      "rm": "코"
    },
    {
      "corp_code": "01407158",
      "corp_name": "이노테나",
      "stock_code": "333050",
      "corp_cls": "K",
      "report_nm": "주권매매거래정지해제              (액면병합 주권 변경상장)",
      "rcept_no": "20260519900399",
      "flr_nm": "코스닥시장본부",
      "rcept_dt": "20260519",
      "rm": "코"
    },
    {
      "corp_code": "00120906",
      "corp_name": "에스아이리소스",
      "stock_code": "065420",
      "corp_cls": "K",
      "report_nm": "기업가치제고계획(자율공시)              ",
      "rcept_no": "20260519900391",
      "flr_nm": "에스아이리소스",
      "rcept_dt": "20260519",
      "rm": "코"
    },
    {
      "corp_code": "01350869",
      "corp_name": "우리금융지주",
      "stock_code": "316140",
      "corp_cls": "Y",
      "report_nm": "기업설명회(IR)개최(안내공시)              ",
      "rcept_no": "20260519800377",
      "flr_nm": "우리금융지주",
      "rcept_dt": "20260519",
      "rm": "유"
    },
    {
      "corp_code": "00577335",
      "corp_name": "대성하이텍",
      "stock_code": "129920",
      "corp_cls": "K",
      "report_nm": "증권발행결과(자율공시)              (제7회차 CB)",
      "rcept_no": "20260519900384",
      "flr_nm": "대성하이텍",
      "rcept_dt": "20260519",
      "rm": "코"
    },
    {
      "corp_code": "00159500",
      "corp_name": "한국종합기술",
      "stock_code": "023350",
      "corp_cls": "Y",
      "report_nm": "[기재정정]단일판매ㆍ공급계약체결              ",
      "rcept_no": "20260519800383",
      "flr_nm": "한국종합기술",
      "rcept_dt": "20260519",
      "rm": "유"
    },
    {
      "corp_code": "00203209",
      "corp_name": "에쎈테크",
      "stock_code": "043340",
      "corp_cls": "K",
      "report_nm": "단기차입금증가결정              ",
      "rcept_no": "20260519900388",
      "flr_nm": "에쎈테크",
      "rcept_dt": "20260519",
      "rm": "코"
    },
    {
      "corp_code": "00130383",
      "corp_name": "서부T&D",
      "stock_code": "006730",
      "corp_cls": "K",
      "report_nm": "기업설명회(IR)개최              ",
      "rcept_no": "20260519900386",
      "flr_nm": "서부T&D",
      "rcept_dt": "20260519",
      "rm": "코"
    },
    {
      "corp_code": "01117246",
      "corp_name": "EMB",
      "stock_code": "278990",
      "corp_cls": "N",
      "report_nm": "기업설명회(IR)개최결과              ",
      "rcept_no": "20260519600378",
      "flr_nm": "EMB",
      "rcept_dt": "20260519",
      "rm": "넥"
    },
    {
      "corp_code": "00563518",
      "corp_name": "비나텍",
      "stock_code": "126340",
      "corp_cls": "K",
      "report_nm": "금전대여결정              ",
      "rcept_no": "20260519900354",
      "flr_nm": "비나텍",
      "rcept_dt": "20260519",
      "rm": "코"
    },
    {
      "corp_code": "00910202",
      "corp_name": "대동고려삼",
      "stock_code": "178600",
      "corp_cls": "N",
      "report_nm": "기업설명회(IR)개최              ",
      "rcept_no": "20260519600374",
      "flr_nm": "대동고려삼",
      "rcept_dt": "20260519",
      "rm": "넥"
    },
    {
      "corp_code": "00522007",
      "corp_name": "크리스에프앤씨",
      "stock_code": "110790",
      "corp_cls": "K",
      "report_nm": "교환사채(해외교환사채포함)발행후만기전사채취득              ",
      "rcept_no": "20260519900373",
      "flr_nm": "크리스에프앤씨",
      "rcept_dt": "20260519",
      "rm": "코"
    },
    {
      "corp_code": "01031229",
      "corp_name": "한국비티비",
      "stock_code": "219750",
      "corp_cls": "K",
      "report_nm": "임시주주총회결과              ",
      "rcept_no": "20260519900282",
      "flr_nm": "한국비티비",
      "rcept_dt": "20260519",
      "rm": "코"
    },
    {
      "corp_code": "00429694",
      "corp_name": "파버나인",
      "stock_code": "177830",
      "corp_cls": "K",
      "report_nm": "[기재정정]주식소각결정              ",
      "rcept_no": "20260519900272",
      "flr_nm": "파버나인",
      "rcept_dt": "20260519",
      "rm": "코"
    },
    {
      "corp_code": "00136402",
      "corp_name": "신송홀딩스",
      "stock_code": "006880",
      "corp_cls": "Y",
      "report_nm": "최대주주등소유주식변동신고서              ",
      "rcept_no": "20260519800348",
      "flr_nm": "신송홀딩스",
      "rcept_dt": "20260519",
      "rm": "유"
    },
    {
      "corp_code": "00356370",
      "corp_name": "LG생활건강",
      "stock_code": "051900",
      "corp_cls": "Y",
      "report_nm": "풍문또는보도에대한해명              ",
      "rcept_no": "20260519800324",
      "flr_nm": "LG생활건강",
      "rcept_dt": "20260519",
      "rm": "유"
    },
    {
      "corp_code": "00532855",
      "corp_name": "한국유니온제약",
      "stock_code": "080720",
      "corp_cls": "K",
      "report_nm": "최대주주변경              ",
      "rcept_no": "20260519900317",
      "flr_nm": "한국유니온제약",
      "rcept_dt": "20260519",
      "rm": "코"
    },
    {
      "corp_code": "00532855",
      "corp_name": "한국유니온제약",
      "stock_code": "080720",
      "corp_cls": "K",
      "report_nm": "증권발행결과(자율공시)              (제3자배정 유상증자-출자전환)",
      "rcept_no": "20260519900316",
      "flr_nm": "한국유니온제약",
      "rcept_dt": "20260519",
      "rm": "코"
    },
    {
      "corp_code": "00249247",
      "corp_name": "YG PLUS",
      "stock_code": "037270",
      "corp_cls": "Y",
      "report_nm": "투자판단관련주요경영사항              ",
      "rcept_no": "20260519800299",
      "flr_nm": "YG PLUS",
      "rcept_dt": "20260519",
      "rm": "유"
    },
    {
      "corp_code": "00244747",
      "corp_name": "파크시스템스",
      "stock_code": "140860",
      "corp_cls": "K",
      "report_nm": "기업설명회(IR)개최              ",
      "rcept_no": "20260519900319",
      "flr_nm": "파크시스템스",
      "rcept_dt": "20260519",
      "rm": "코"
    },
    {
      "corp_code": "01226234",
      "corp_name": "와이바이오로직스",
      "stock_code": "338840",
      "corp_cls": "K",
      "report_nm": "임시주주총회결과              ",
      "rcept_no": "20260519900302",
      "flr_nm": "와이바이오로직스",
      "rcept_dt": "20260519",
      "rm": "코"
    },
    {
      "corp_code": "00206659",
      "corp_name": "이랜텍",
      "stock_code": "054210",
      "corp_cls": "K",
      "report_nm": "기업설명회(IR)개최              ",
      "rcept_no": "20260519900315",
      "flr_nm": "이랜텍",
      "rcept_dt": "20260519",
      "rm": "코"
    },
    {
      "corp_code": "00114765",
      "corp_name": "케이비아이동국실업",
      "stock_code": "001620",
      "corp_cls": "Y",
      "report_nm": "최대주주등소유주식변동신고서              ",
      "rcept_no": "20260519800314",
      "flr_nm": "케이비아이동국실업",
      "rcept_dt": "20260519",
      "rm": "유"
    },
    {
      "corp_code": "00899459",
      "corp_name": "레이언스",
      "stock_code": "228850",
      "corp_cls": "K",
      "report_nm": "기업설명회(IR)개최              ",
      "rcept_no": "20260519900304",
      "flr_nm": "레이언스",
      "rcept_dt": "20260519",
      "rm": "코"
    },
    {
      "corp_code": "00127167",
      "corp_name": "삼영무역",
      "stock_code": "002810",
      "corp_cls": "Y",
      "report_nm": "최대주주등소유주식변동신고서              ",
      "rcept_no": "20260519800298",
      "flr_nm": "삼영무역",
      "rcept_dt": "20260519",
      "rm": "유"
    },
    {
      "corp_code": "00159218",
      "corp_name": "한전KPS",
      "stock_code": "051600",
      "corp_cls": "Y",
      "report_nm": "기업설명회(IR)개최(안내공시)              ",
      "rcept_no": "20260519800297",
      "flr_nm": "한전KPS",
      "rcept_dt": "20260519",
      "rm": "유"
    },
    {
      "corp_code": "01042359",
      "corp_name": "지엘팜텍",
      "stock_code": "204840",
      "corp_cls": "K",
      "report_nm": "주주명부폐쇄기간또는기준일설정              ",
      "rcept_no": "20260519900291",
      "flr_nm": "지엘팜텍",
      "rcept_dt": "20260519",
      "rm": "코"
    },
    {
      "corp_code": "00157399",
      "corp_name": "한솔테크닉스",
      "stock_code": "004710",
      "corp_cls": "Y",
      "report_nm": "유상증자또는주식관련사채등의발행결과(자율공시)              ",
      "rcept_no": "20260519800290",
      "flr_nm": "한솔테크닉스",
      "rcept_dt": "20260519",
      "rm": "유"
    },
    {
      "corp_code": "01042359",
      "corp_name": "지엘팜텍",
      "stock_code": "204840",
      "corp_cls": "K",
      "report_nm": "주주총회소집결의              (임시주주총회)",
      "rcept_no": "20260519900273",
      "flr_nm": "지엘팜텍",
      "rcept_dt": "20260519",
      "rm": "코"
    },
    {
      "corp_code": "00556712",
      "corp_name": "힘스",
      "stock_code": "238490",
      "corp_cls": "K",
      "report_nm": "[기재정정]단일판매ㆍ공급계약체결              ",
      "rcept_no": "20260519900268",
      "flr_nm": "힘스",
      "rcept_dt": "20260519",
      "rm": "코"
    },
    {
      "corp_code": "00428729",
      "corp_name": "대호에이엘",
      "stock_code": "069460",
      "corp_cls": "Y",
      "report_nm": "소송등의판결ㆍ결정              ",
      "rcept_no": "20260519800279",
      "flr_nm": "대호에이엘",
      "rcept_dt": "20260519",
      "rm": "유"
    },
    {
      "corp_code": "01366000",
      "corp_name": "태성",
      "stock_code": "323280",
      "corp_cls": "K",
      "report_nm": "단일판매ㆍ공급계약체결              ",
      "rcept_no": "20260519900252",
      "flr_nm": "태성",
      "rcept_dt": "20260519",
      "rm": "코"
    },
    {
      "corp_code": "00535676",
      "corp_name": "테크윙",
      "stock_code": "089030",
      "corp_cls": "K",
      "report_nm": "단일판매ㆍ공급계약체결(자율공시)              ",
      "rcept_no": "20260519900243",
      "flr_nm": "테크윙",
      "rcept_dt": "20260519",
      "rm": "코"
    },
    {
      "corp_code": "00926522",
      "corp_name": "테고사이언스",
      "stock_code": "191420",
      "corp_cls": "K",
      "report_nm": "타법인주식및출자증권취득결정(자율공시)              ",
      "rcept_no": "20260519900228",
      "flr_nm": "테고사이언스",
      "rcept_dt": "20260519",
      "rm": "코"
    },
    {
      "corp_code": "00264255",
      "corp_name": "바텍",
      "stock_code": "043150",
      "corp_cls": "K",
      "report_nm": "기업설명회(IR)개최              ",
      "rcept_no": "20260519900276",
      "flr_nm": "바텍",
      "rcept_dt": "20260519",
      "rm": "코"
    },
    {
      "corp_code": "00106641",
      "corp_name": "기아",
      "stock_code": "000270",
      "corp_cls": "Y",
      "report_nm": "기업설명회(IR)개최(안내공시)              ",
      "rcept_no": "20260519800275",
      "flr_nm": "기아",
      "rcept_dt": "20260519",
      "rm": "유"
    },
    {
      "corp_code": "00106641",
      "corp_name": "기아",
      "stock_code": "000270",
      "corp_cls": "Y",
      "report_nm": "기업설명회(IR)개최(안내공시)              ",
      "rcept_no": "20260519800271",
      "flr_nm": "기아",
      "rcept_dt": "20260519",
      "rm": "유"
    },
    {
      "corp_code": "00159209",
      "corp_name": "한전기술",
      "stock_code": "052690",
      "corp_cls": "Y",
      "report_nm": "임시주주총회결과              ",
      "rcept_no": "20260519800254",
      "flr_nm": "한전기술",
      "rcept_dt": "20260519",
      "rm": "유"
    },
    {
      "corp_code": "00610083",
      "corp_name": "비아트론",
      "stock_code": "141000",
      "corp_cls": "K",
      "report_nm": "단일판매ㆍ공급계약체결              ",
      "rcept_no": "20260519900258",
      "flr_nm": "비아트론",
      "rcept_dt": "20260519",
      "rm": "코"
    },
    {
      "corp_code": "01208751",
      "corp_name": "아이에스티이",
      "stock_code": "212710",
      "corp_cls": "K",
      "report_nm": "기업설명회(IR)개최              ",
      "rcept_no": "20260519900247",
      "flr_nm": "아이에스티이",
      "rcept_dt": "20260519",
      "rm": "코"
    },
    {
      "corp_code": "00491415",
      "corp_name": "인포바인",
      "stock_code": "115310",
      "corp_cls": "K",
      "report_nm": "수시공시의무관련사항(공정공시)              (주주가치 제고를 위한 자기주식 소각 예고)",
      "rcept_no": "20260519900241",
      "flr_nm": "인포바인",
      "rcept_dt": "20260519",
      "rm": "코"
    },
    {
      "corp_code": "00556615",
      "corp_name": "모바일어플라이언스",
      "stock_code": "087260",
      "corp_cls": "K",
      "report_nm": "대표이사변경              ",
      "rcept_no": "20260519900245",
      "flr_nm": "모바일어플라이언스",
      "rcept_dt": "20260519",
      "rm": "코"
    },
    {
      "corp_code": "00130879",
      "corp_name": "서울식품공업",
      "stock_code": "004410",
      "corp_cls": "Y",
      "report_nm": "최대주주등소유주식변동신고서              ",
      "rcept_no": "20260519800238",
      "flr_nm": "서울식품공업",
      "rcept_dt": "20260519",
      "rm": "유"
    },
    {
      "corp_code": "00147860",
      "corp_name": "에스엠벡셀",
      "stock_code": "010580",
      "corp_cls": "Y",
      "report_nm": "최대주주등소유주식변동신고서              ",
      "rcept_no": "20260519800236",
      "flr_nm": "에스엠벡셀",
      "rcept_dt": "20260519",
      "rm": "유"
    },
    {
      "corp_code": "01042359",
      "corp_name": "지엘팜텍",
      "stock_code": "204840",
      "corp_cls": "K",
      "report_nm": "주식병합결정              ",
      "rcept_no": "20260519900234",
      "flr_nm": "지엘팜텍",
      "rcept_dt": "20260519",
      "rm": "코"
    },
    {
      "corp_code": "00108612",
      "corp_name": "DS단석",
      "stock_code": "017860",
      "corp_cls": "Y",
      "report_nm": "기업설명회(IR)개최(안내공시)              ",
      "rcept_no": "20260519800222",
      "flr_nm": "DS단석",
      "rcept_dt": "20260519",
      "rm": "유"
    },
    {
      "corp_code": "01649204",
      "corp_name": "달바글로벌",
      "stock_code": "483650",
      "corp_cls": "Y",
      "report_nm": "기타안내사항(안내공시)              ",
      "rcept_no": "20260519800212",
      "flr_nm": "달바글로벌",
      "rcept_dt": "20260519",
      "rm": "유"
    },
    {
      "corp_code": "01506990",
      "corp_name": "옵티코어",
      "stock_code": "380540",
      "corp_cls": "K",
      "report_nm": "단일판매ㆍ공급계약체결              ",
      "rcept_no": "20260519900209",
      "flr_nm": "옵티코어",
      "rcept_dt": "20260519",
      "rm": "코"
    },
    {
      "corp_code": "00526696",
      "corp_name": "웨이브일렉트로",
      "stock_code": "095270",
      "corp_cls": "K",
      "report_nm": "[기재정정]주주총회소집결의              (임시주주총회)",
      "rcept_no": "20260519900200",
      "flr_nm": "웨이브일렉트로",
      "rcept_dt": "20260519",
      "rm": "코"
    },
    {
      "corp_code": "00364467",
      "corp_name": "드림어스컴퍼니",
      "stock_code": "060570",
      "corp_cls": "K",
      "report_nm": "주식병합결정              ",
      "rcept_no": "20260519900199",
      "flr_nm": "드림어스컴퍼니",
      "rcept_dt": "20260519",
      "rm": "코"
    },
    {
      "corp_code": "00364467",
      "corp_name": "드림어스컴퍼니",
      "stock_code": "060570",
      "corp_cls": "K",
      "report_nm": "주주명부폐쇄기간또는기준일설정              ",
      "rcept_no": "20260519900190",
      "flr_nm": "드림어스컴퍼니",
      "rcept_dt": "20260519",
      "rm": "코"
    },
    {
      "corp_code": "00266961",
      "corp_name": "NAVER",
      "stock_code": "035420",
      "corp_cls": "Y",
      "report_nm": "풍문또는보도에대한해명(미확정)              ",
      "rcept_no": "20260519800168",
      "flr_nm": "NAVER",
      "rcept_dt": "20260519",
      "rm": "유"
    },
    {
      "corp_code": "00174208",
      "corp_name": "진성티이씨",
      "stock_code": "036890",
      "corp_cls": "K",
      "report_nm": "교환청구권행사              ",
      "rcept_no": "20260519900175",
      "flr_nm": "진성티이씨",
      "rcept_dt": "20260519",
      "rm": "코"
    },
    {
      "corp_code": "01061327",
      "corp_name": "클래시스",
      "stock_code": "214150",
      "corp_cls": "K",
      "report_nm": "기업설명회(IR)개최              ",
      "rcept_no": "20260519900173",
      "flr_nm": "클래시스",
      "rcept_dt": "20260519",
      "rm": "코"
    },
    {
      "corp_code": "00878696",
      "corp_name": "에스케이바이오팜",
      "stock_code": "326030",
      "corp_cls": "Y",
      "report_nm": "기업설명회(IR)개최(안내공시)              ",
      "rcept_no": "20260519800163",
      "flr_nm": "에스케이바이오팜",
      "rcept_dt": "20260519",
      "rm": "유"
    },
    {
      "corp_code": "00163716",
      "corp_name": "한창",
      "stock_code": "005110",
      "corp_cls": "Y",
      "report_nm": "소송등의제기ㆍ신청(일정금액이상의청구)              ",
      "rcept_no": "20260519800143",
      "flr_nm": "한창",
      "rcept_dt": "20260519",
      "rm": "유"
    },
    {
      "corp_code": "00353878",
      "corp_name": "다스코",
      "stock_code": "058730",
      "corp_cls": "Y",
      "report_nm": "[기재정정]단일판매ㆍ공급계약체결              ",
      "rcept_no": "20260519800147",
      "flr_nm": "다스코",
      "rcept_dt": "20260519",
      "rm": "유"
    },
    {
      "corp_code": "01035368",
      "corp_name": "티에프이",
      "stock_code": "425420",
      "corp_cls": "K",
      "report_nm": "기업설명회(IR)개최              ",
      "rcept_no": "20260519900129",
      "flr_nm": "티에프이",
      "rcept_dt": "20260519",
      "rm": "코"
    },
    {
      "corp_code": "00415646",
      "corp_name": "드림텍",
      "stock_code": "192650",
      "corp_cls": "Y",
      "report_nm": "주식소각결정              ",
      "rcept_no": "20260519800138",
      "flr_nm": "드림텍",
      "rcept_dt": "20260519",
      "rm": "유"
    },
    {
      "corp_code": "00927558",
      "corp_name": "유바이오로직스",
      "stock_code": "206650",
      "corp_cls": "K",
      "report_nm": "단일판매ㆍ공급계약체결(자율공시)              ",
      "rcept_no": "20260519900122",
      "flr_nm": "유바이오로직스",
      "rcept_dt": "20260519",
      "rm": "코"
    },
    {
      "corp_code": "00357740",
      "corp_name": "NHN KCP",
      "stock_code": "060250",
      "corp_cls": "K",
      "report_nm": "기업설명회(IR)개최              ",
      "rcept_no": "20260519900095",
      "flr_nm": "NHN KCP",
      "rcept_dt": "20260519",
      "rm": "코"
    },
    {
      "corp_code": "00332149",
      "corp_name": "코스닥시장본부",
      "stock_code": "",
      "corp_cls": "E",
      "report_nm": "기타시장안내(금일NXT경쟁매매대상종목지정으로인한KRX시간외단일가매매제외종목안내(코스닥시장))              ",
      "rcept_no": "20260519900012",
      "flr_nm": "코스닥시장본부",
      "rcept_dt": "20260519",
      "rm": "코"
    },
    {
      "corp_code": "00420301",
      "corp_name": "유가증권시장본부",
      "stock_code": "",
      "corp_cls": "E",
      "report_nm": "기타시장안내(금일NXT경쟁매매대상종목지정으로인한KRX시간외단일가매매제외종목안내(유가증권시장))              ",
      "rcept_no": "20260519800008",
      "flr_nm": "유가증권시장본부",
      "rcept_dt": "20260519",
      "rm": "유"
    },
    {
      "corp_code": "00297448",
      "corp_name": "플래스크",
      "stock_code": "041590",
      "corp_cls": "K",
      "report_nm": "대표이사변경              ",
      "rcept_no": "20260519900001",
      "flr_nm": "플래스크",
      "rcept_dt": "20260519",
      "rm": "코"
    },
    {
      "corp_code": "01159853",
      "corp_name": "휴온스",
      "stock_code": "243070",
      "corp_cls": "K",
      "report_nm": "주권매매거래정지해제              (우회상장 미해당)",
      "rcept_no": "20260518901004",
      "flr_nm": "코스닥시장본부",
      "rcept_dt": "20260518",
      "rm": "코"
    },
    {
      "corp_code": "00390408",
      "corp_name": "인크레더블버즈",
      "stock_code": "064090",
      "corp_cls": "K",
      "report_nm": "주권매매거래정지기간변경              (상장폐지 사유 발생)",
      "rcept_no": "20260518901000",
      "flr_nm": "코스닥시장본부",
      "rcept_dt": "20260518",
      "rm": "코"
    },
    {
      "corp_code": "01110678",
      "corp_name": "유틸렉스",
      "stock_code": "263050",
      "corp_cls": "K",
      "report_nm": "주권매매거래정지기간변경              (상장폐지 사유 발생)",
      "rcept_no": "20260518900999",
      "flr_nm": "코스닥시장본부",
      "rcept_dt": "20260518",
      "rm": "코"
    },
    {
      "corp_code": "01110678",
      "corp_name": "유틸렉스",
      "stock_code": "263050",
      "corp_cls": "K",
      "report_nm": "기타시장안내              (기업심사위원회 개최 결과 안내)",
      "rcept_no": "20260518900996",
      "flr_nm": "코스닥시장본부",
      "rcept_dt": "20260518",
      "rm": "코"
    },
    {
      "corp_code": "00390408",
      "corp_name": "인크레더블버즈",
      "stock_code": "064090",
      "corp_cls": "K",
      "report_nm": "기타시장안내              (기업심사위원회 개최 결과 안내)",
      "rcept_no": "20260518900995",
      "flr_nm": "코스닥시장본부",
      "rcept_dt": "20260518",
      "rm": "코"
    },
    {
      "corp_code": "00120906",
      "corp_name": "에스아이리소스",
      "stock_code": "065420",
      "corp_cls": "K",
      "report_nm": "소송등의제기ㆍ신청(경영권분쟁소송)              (직무집행정지 가처분)",
      "rcept_no": "20260518900959",
      "flr_nm": "에스아이리소스",
      "rcept_dt": "20260518",
      "rm": "코"
    },
    {
      "corp_code": "01042979",
      "corp_name": "휴마시스",
      "stock_code": "205470",
      "corp_cls": "K",
      "report_nm": "최대주주변경              ",
      "rcept_no": "20260518900972",
      "flr_nm": "휴마시스",
      "rcept_dt": "20260518",
      "rm": "코"
    },
    {
      "corp_code": "00556615",
      "corp_name": "모바일어플라이언스",
      "stock_code": "087260",
      "corp_cls": "K",
      "report_nm": "최대주주변경을수반하는주식담보제공계약해제ㆍ취소등              ",
      "rcept_no": "20260518900968",
      "flr_nm": "모바일어플라이언스",
      "rcept_dt": "20260518",
      "rm": "코"
    },
    {
      "corp_code": "00997812",
      "corp_name": "코미코",
      "stock_code": "183300",
      "corp_cls": "K",
      "report_nm": "[기재정정]타인에대한채무보증결정              ",
      "rcept_no": "20260518900971",
      "flr_nm": "코미코",
      "rcept_dt": "20260518",
      "rm": "코"
    },
    {
      "corp_code": "01159853",
      "corp_name": "휴온스",
      "stock_code": "243070",
      "corp_cls": "K",
      "report_nm": "주권매매거래정지              (우회상장여부 및 요건충족확인)",
      "rcept_no": "20260518900965",
      "flr_nm": "코스닥시장본부",
      "rcept_dt": "20260518",
      "rm": "코"
    },
    {
      "corp_code": "00997812",
      "corp_name": "코미코",
      "stock_code": "183300",
      "corp_cls": "K",
      "report_nm": "[기재정정]타인에대한채무보증결정              ",
      "rcept_no": "20260518900969",
      "flr_nm": "코미코",
      "rcept_dt": "20260518",
      "rm": "코"
    },
    {
      "corp_code": "00141404",
      "corp_name": "블루산업개발",
      "stock_code": "006740",
      "corp_cls": "Y",
      "report_nm": "유상증자또는주식관련사채등의발행결과(자율공시)              ",
      "rcept_no": "20260518800944",
      "flr_nm": "블루산업개발",
      "rcept_dt": "20260518",
      "rm": "유"
    },
    {
      "corp_code": "01714997",
      "corp_name": "신한글로벌액티브리츠",
      "stock_code": "481850",
      "corp_cls": "Y",
      "report_nm": "수시공시의무관련사항(공정공시)              ",
      "rcept_no": "20260518800942",
      "flr_nm": "신한글로벌액티브리츠",
      "rcept_dt": "20260518",
      "rm": "유"
    },
    {
      "corp_code": "00556615",
      "corp_name": "모바일어플라이언스",
      "stock_code": "087260",
      "corp_cls": "K",
      "report_nm": "최대주주변경              ",
      "rcept_no": "20260518900938",
      "flr_nm": "모바일어플라이언스",
      "rcept_dt": "20260518",
      "rm": "코"
    },
    {
      "corp_code": "00120906",
      "corp_name": "에스아이리소스",
      "stock_code": "065420",
      "corp_cls": "K",
      "report_nm": "[기재정정]주주명부폐쇄기간또는기준일설정              ",
      "rcept_no": "20260518900943",
      "flr_nm": "에스아이리소스",
      "rcept_dt": "20260518",
      "rm": "코"
    },
    {
      "corp_code": "00149655",
      "corp_name": "삼성물산",
      "stock_code": "028260",
      "corp_cls": "Y",
      "report_nm": "기업설명회(IR)개최(안내공시)              ",
      "rcept_no": "20260518800918",
      "flr_nm": "삼성물산",
      "rcept_dt": "20260518",
      "rm": "유"
    },
    {
      "corp_code": "00120906",
      "corp_name": "에스아이리소스",
      "stock_code": "065420",
      "corp_cls": "K",
      "report_nm": "[기재정정]주주총회소집결의              (임시주주총회)",
      "rcept_no": "20260518900914",
      "flr_nm": "에스아이리소스",
      "rcept_dt": "20260518",
      "rm": "코"
    },
    {
      "corp_code": "00660033",
      "corp_name": "씨엔플러스",
      "stock_code": "115530",
      "corp_cls": "K",
      "report_nm": "전환가액의조정              (제8회차)",
      "rcept_no": "20260518900909",
      "flr_nm": "씨엔플러스",
      "rcept_dt": "20260518",
      "rm": "코"
    },
    {
      "corp_code": "00660033",
      "corp_name": "씨엔플러스",
      "stock_code": "115530",
      "corp_cls": "K",
      "report_nm": "전환가액의조정              (제7회차)",
      "rcept_no": "20260518900910",
      "flr_nm": "씨엔플러스",
      "rcept_dt": "20260518",
      "rm": "코"
    }
  ]
}