{
  "status": "000",
  "message": "정상",
  "list": [
    {
      "rcept_no": "20260522000348",
      "corp_cls": "K",
      "corp_code": "00604426",
      "corp_name": "인터로조",
      "bddd": "-",
      "od_a_at_t": "-",
      "od_a_at_b": "-",
      "adt_a_atn": "-",
      "aq_wtn_div_ostk": "180,303",
      "aq_wtn_div_ostk_rt": "1.58",
      "aq_wtn_div_estk": "-",
      "aq_wtn_div_estk_rt": "-",
      "eaq_ostk": "-",
      "eaq_ostk_rt": "-",
      "eaq_estk": "-",
      "eaq_estk_rt": "-",
      "ctr_prc_bfcc": "3,000,000,000",
      "ctr_prc_atcc": "-",
      "ctr_pd_bfcc_bgd": "2025년 11월 24일",
      "ctr_pd_bfcc_edd": "2026년 05월 22일",
      "cc_pp": "신탁계약 기간 만료에 의한 해지",
      "cc_int": "KB증권",
      "cc_prd": "2026년 05월 22일",
      "tp_rm_atcc": "KB증권 계좌에 취득 자사주 보유"
    }
  ]
}