{
  "status": "000",
  "message": "정상",
  "list": [
    {
      "rcept_no": "20260211000385",
      "corp_cls": "Y",
      "corp_code": "00428251",
      "corp_name": "현대백화점",
      "od_a_at_t": "5",
      "od_a_at_b": "-",
      "adt_a_atn": "-",
      "aqpln_stk_ostk": "194,085",
      "aqpln_stk_estk": "-",
      "aqpln_prc_ostk": "21,000,000,000",
      "aqpln_prc_estk": "-",
      "aqexpd_bgd": "2026년 02월 12일",
      "aqexpd_edd": "2026년 05월 11일",
      "hdexpd_bgd": "-",
      "hdexpd_edd": "-",
      "aq_pp": "주주환원정책을 통한 주주가치 제고",
      "aq_mth": "유가증권 시장을 통한 장내매수",
      "cs_iv_bk": "KB증권 (KB Securities Co.,Ltd.)",
      "aq_wtn_div_ostk": "778,808",
      "aq_wtn_div_ostk_rt": "3.4",
      "aq_wtn_div_estk": "-",
      "aq_wtn_div_estk_rt": "-",
      "eaq_ostk": "285,093",
      "eaq_ostk_rt": "1.3",
      "eaq_estk": "-",
      "eaq_estk_rt": "-",
      "aq_dd": "2026년 02월 11일",
      "d1_prodlm_ostk": "33,481",
      "d1_prodlm_estk": "-"
    }
  ]
}